[
    {
        "object": "block",
        "id": "1f422086-c5a0-807e-bd40-e054da7349a6",
        "parent": {
            "type": "page_id",
            "page_id": "1f422086-c5a0-807b-bd4d-ffe3502e74f8"
        },
        "created_time": "2025-05-15T16:11:00.000Z",
        "last_edited_time": "2025-05-15T16:11:00.000Z",
        "created_by": {
            "object": "user",
            "id": "66828f29-35c2-40b1-9346-8b0ef9c20741"
        },
        "last_edited_by": {
            "object": "user",
            "id": "66828f29-35c2-40b1-9346-8b0ef9c20741"
        },
        "has_children": false,
        "archived": false,
        "in_trash": false,
        "type": "heading_1",
        "heading_1": {
            "rich_text": [
                {
                    "type": "text",
                    "text": {
                        "content": "Reason : ",
                        "link": null
                    },
                    "annotations": {
                        "bold": false,
                        "italic": false,
                        "strikethrough": false,
                        "underline": false,
                        "code": false,
                        "color": "default"
                    },
                    "plain_text": "Reason : ",
                    "href": null
                }
            ],
            "is_toggleable": false,
            "color": "default"
        }
    },
    {
        "object": "block",
        "id": "1f422086-c5a0-8012-a5be-f9c7704b3986",
        "parent": {
            "type": "page_id",
            "page_id": "1f422086-c5a0-807b-bd4d-ffe3502e74f8"
        },
        "created_time": "2025-05-15T16:11:00.000Z",
        "last_edited_time": "2025-05-15T16:11:00.000Z",
        "created_by": {
            "object": "user",
            "id": "66828f29-35c2-40b1-9346-8b0ef9c20741"
        },
        "last_edited_by": {
            "object": "user",
            "id": "66828f29-35c2-40b1-9346-8b0ef9c20741"
        },
        "has_children": false,
        "archived": false,
        "in_trash": false,
        "type": "paragraph",
        "paragraph": {
            "rich_text": [
                {
                    "type": "text",
                    "text": {
                        "content": "\uc65c \ud574?",
                        "link": null
                    },
                    "annotations": {
                        "bold": true,
                        "italic": false,
                        "strikethrough": false,
                        "underline": false,
                        "code": false,
                        "color": "gray"
                    },
                    "plain_text": "\uc65c \ud574?",
                    "href": null
                }
            ],
            "color": "default"
        }
    },
    {
        "object": "block",
        "id": "1f422086-c5a0-8037-8f26-d8e6bcb54b35",
        "parent": {
            "type": "page_id",
            "page_id": "1f422086-c5a0-807b-bd4d-ffe3502e74f8"
        },
        "created_time": "2025-05-15T16:13:00.000Z",
        "last_edited_time": "2025-05-15T16:21:00.000Z",
        "created_by": {
            "object": "user",
            "id": "66828f29-35c2-40b1-9346-8b0ef9c20741"
        },
        "last_edited_by": {
            "object": "user",
            "id": "66828f29-35c2-40b1-9346-8b0ef9c20741"
        },
        "has_children": false,
        "archived": false,
        "in_trash": false,
        "type": "to_do",
        "to_do": {
            "rich_text": [
                {
                    "type": "text",
                    "text": {
                        "content": "src/main/java\ub294 \uc18c\uc2a4\ucf54\ub4dc \uc788\ub294 \ud30c\uc77c\uc785\ub2c8\ub2e4. \uadf8\ub7fc \ub8e8\ud2b8 \uc544\ub798 src\\main\\webapp\uc740 \ubb58\uae4c\uc694?",
                        "link": null
                    },
                    "annotations": {
                        "bold": false,
                        "italic": false,
                        "strikethrough": false,
                        "underline": false,
                        "code": false,
                        "color": "default"
                    },
                    "plain_text": "src/main/java\ub294 \uc18c\uc2a4\ucf54\ub4dc \uc788\ub294 \ud30c\uc77c\uc785\ub2c8\ub2e4. \uadf8\ub7fc \ub8e8\ud2b8 \uc544\ub798 src\\main\\webapp\uc740 \ubb58\uae4c\uc694?",
                    "href": null
                }
            ],
            "checked": false,
            "color": "default"
        }
    },
    {
        "object": "block",
        "id": "1f422086-c5a0-8023-ae1e-c1d1ec2344f3",
        "parent": {
            "type": "page_id",
            "page_id": "1f422086-c5a0-807b-bd4d-ffe3502e74f8"
        },
        "created_time": "2025-05-15T16:13:00.000Z",
        "last_edited_time": "2025-05-15T16:13:00.000Z",
        "created_by": {
            "object": "user",
            "id": "66828f29-35c2-40b1-9346-8b0ef9c20741"
        },
        "last_edited_by": {
            "object": "user",
            "id": "66828f29-35c2-40b1-9346-8b0ef9c20741"
        },
        "has_children": false,
        "archived": false,
        "in_trash": false,
        "type": "image",
        "image": {
            "caption": [],
            "type": "file",
            "file": {
                "url": "https://prod-files-secure.s3.us-west-2.amazonaws.com/a3e11562-4372-438f-82a2-d7c92f037b47/e8fce065-6e9b-4758-8201-eb2568e895af/%EC%8A%A4%ED%81%AC%EB%A6%B0%EC%83%B7_2025-05-16_010741.png?X-Amz-Algorithm=AWS4-HMAC-SHA256&X-Amz-Content-Sha256=UNSIGNED-PAYLOAD&X-Amz-Credential=ASIAZI2LB466VWLZ4U76%2F20250615%2Fus-west-2%2Fs3%2Faws4_request&X-Amz-Date=20250615T072733Z&X-Amz-Expires=3600&X-Amz-Security-Token=IQoJb3JpZ2luX2VjEFUaCXVzLXdlc3QtMiJHMEUCIQCqelqKlfnbsQZYm1szol2tgQLmh17VJqCCstac1LP7ygIgJVsKpR2vFW2uthPaD9pi9sSEwaZpD3OdPuhnQ0jtFW4q%2FwMIPhAAGgw2Mzc0MjMxODM4MDUiDBnJLh4QRU8eAuYMLyrcAwpBZRAHAubg51G2OT0SrexbjmxrMWab6v%2FK3Nbx%2B1I9bvZHgPEh1Qj%2BhXgnTHlWrbVeHElN5WpK3mmGcNDCTukCpCgIYosfgyIt6sqgt3L47JEacYN5fImfAUPxDkflxB9LUSqTV3zEr5EEh%2Bn5raqhChYCSVbqj2R4i711VFVrgkBgfG9mpJenDCo9%2Fl8%2FNoI0P6ZDJqBbAeDEBz1%2FQQv7HCs5LjjEgFc2kTwgUWp0cL%2B3n2v8Kt8KW7KiSNhINIj2zVSar3HqtvN7X1ZBiGQLFIJilIQhmGr7wwWtw91IsJkj292PQJj8K5z827tjjpvY8TgoZ3lBEcuHcuqLxGAu0udns4WnAGJrKYDqorQolQbFSql2sLf53%2BPf%2B2%2Bc5B9tQVo%2FBbPr0Y7VmYCnPiaUYHwl4JIhE93yyPpVnrUSx5icV%2Fypuhf1KmI7iQI8YZowPxBB9V%2FT6v5xYfXiuY2sIo5WKR9iNT2THKYZR%2BN3pFjj%2Bt9bQN9zMS41ip5BF7HH1vGHihc2Mv%2FgdY9CpVcF4L7WVFZ60rkCnaE6jVLZOMqFBPrsP2fn5xZgu9n5Y47jUsoRtEeu8Wa%2F5DSBIH%2F%2B%2BbwyTW8as4a5zMX0TXSsOhKBj7svS2uP1pHuMLitucIGOqUBRiZ3Fs3Icty%2BT%2BYXQv5pKwP8IAMzjore4R%2B2wj5HjVUacU3Lzh2rq18sPc3hCy17K%2Fx%2FNPWESK7bcAl64%2BIis8YBN07HMmwiDlPMUEX85kf2tBuPMRMmVLCiPkvWq06XuCKwU%2BYFj84YHsIgShQSf2TtC5PvHAPQebbERmEzpPDo4Rk6tGtGn1saq2HLX9Q5y7JbJtjg6eAvktriHlYaFksht3Px&X-Amz-Signature=e309045513d2a6c945db53bf2bb5e7364bac6312b093a2cffd1b614c95c4380e&X-Amz-SignedHeaders=host&x-amz-checksum-mode=ENABLED&x-id=GetObject",
                "expiry_time": "2025-06-15T08:27:33.170Z"
            }
        }
    },
    {
        "object": "block",
        "id": "1f422086-c5a0-8070-8abc-d64e674df74d",
        "parent": {
            "type": "page_id",
            "page_id": "1f422086-c5a0-807b-bd4d-ffe3502e74f8"
        },
        "created_time": "2025-05-15T16:18:00.000Z",
        "last_edited_time": "2025-05-15T16:18:00.000Z",
        "created_by": {
            "object": "user",
            "id": "66828f29-35c2-40b1-9346-8b0ef9c20741"
        },
        "last_edited_by": {
            "object": "user",
            "id": "66828f29-35c2-40b1-9346-8b0ef9c20741"
        },
        "has_children": false,
        "archived": false,
        "in_trash": false,
        "type": "to_do",
        "to_do": {
            "rich_text": [
                {
                    "type": "text",
                    "text": {
                        "content": "\uc774\ud074\ub9bd\uc2a4\uc5d0\uc11c src\ub97c \ub450\uac1c\ub85c \ub098\ub220\ub193\uc740 \uc774\uc720",
                        "link": null
                    },
                    "annotations": {
                        "bold": false,
                        "italic": false,
                        "strikethrough": false,
                        "underline": false,
                        "code": false,
                        "color": "default"
                    },
                    "plain_text": "\uc774\ud074\ub9bd\uc2a4\uc5d0\uc11c src\ub97c \ub450\uac1c\ub85c \ub098\ub220\ub193\uc740 \uc774\uc720",
                    "href": null
                }
            ],
            "checked": false,
            "color": "default"
        }
    },
    {
        "object": "block",
        "id": "1f422086-c5a0-803e-8a73-c81afb5d8e57",
        "parent": {
            "type": "page_id",
            "page_id": "1f422086-c5a0-807b-bd4d-ffe3502e74f8"
        },
        "created_time": "2025-05-15T16:11:00.000Z",
        "last_edited_time": "2025-05-15T16:11:00.000Z",
        "created_by": {
            "object": "user",
            "id": "66828f29-35c2-40b1-9346-8b0ef9c20741"
        },
        "last_edited_by": {
            "object": "user",
            "id": "66828f29-35c2-40b1-9346-8b0ef9c20741"
        },
        "has_children": false,
        "archived": false,
        "in_trash": false,
        "type": "heading_1",
        "heading_1": {
            "rich_text": [
                {
                    "type": "text",
                    "text": {
                        "content": "Action : ",
                        "link": null
                    },
                    "annotations": {
                        "bold": false,
                        "italic": false,
                        "strikethrough": false,
                        "underline": false,
                        "code": false,
                        "color": "default"
                    },
                    "plain_text": "Action : ",
                    "href": null
                }
            ],
            "is_toggleable": false,
            "color": "default"
        }
    },
    {
        "object": "block",
        "id": "1f422086-c5a0-80c3-9498-c557ab3ec6ed",
        "parent": {
            "type": "page_id",
            "page_id": "1f422086-c5a0-807b-bd4d-ffe3502e74f8"
        },
        "created_time": "2025-05-15T16:11:00.000Z",
        "last_edited_time": "2025-05-15T16:11:00.000Z",
        "created_by": {
            "object": "user",
            "id": "66828f29-35c2-40b1-9346-8b0ef9c20741"
        },
        "last_edited_by": {
            "object": "user",
            "id": "66828f29-35c2-40b1-9346-8b0ef9c20741"
        },
        "has_children": false,
        "archived": false,
        "in_trash": false,
        "type": "paragraph",
        "paragraph": {
            "rich_text": [
                {
                    "type": "text",
                    "text": {
                        "content": "\ubb58 \ud588\uc5b4?",
                        "link": null
                    },
                    "annotations": {
                        "bold": true,
                        "italic": false,
                        "strikethrough": false,
                        "underline": false,
                        "code": false,
                        "color": "gray"
                    },
                    "plain_text": "\ubb58 \ud588\uc5b4?",
                    "href": null
                }
            ],
            "color": "default"
        }
    },
    {
        "object": "block",
        "id": "1f422086-c5a0-80c0-a9eb-c35deb6549a9",
        "parent": {
            "type": "page_id",
            "page_id": "1f422086-c5a0-807b-bd4d-ffe3502e74f8"
        },
        "created_time": "2025-05-15T16:16:00.000Z",
        "last_edited_time": "2025-05-15T16:17:00.000Z",
        "created_by": {
            "object": "user",
            "id": "66828f29-35c2-40b1-9346-8b0ef9c20741"
        },
        "last_edited_by": {
            "object": "user",
            "id": "66828f29-35c2-40b1-9346-8b0ef9c20741"
        },
        "has_children": false,
        "archived": false,
        "in_trash": false,
        "type": "paragraph",
        "paragraph": {
            "rich_text": [
                {
                    "type": "text",
                    "text": {
                        "content": "\uac01\uac01 \ub2e4\ub978 src\ud30c\uc77c\uc774 \uc544\ub2cc \uac19\uc740 src/main \uc544\ub798 java\uc640 webapp\uac00 \uc788\ub294\uac83 \uc774\ub2e4.",
                        "link": null
                    },
                    "annotations": {
                        "bold": false,
                        "italic": false,
                        "strikethrough": false,
                        "underline": false,
                        "code": false,
                        "color": "default"
                    },
                    "plain_text": "\uac01\uac01 \ub2e4\ub978 src\ud30c\uc77c\uc774 \uc544\ub2cc \uac19\uc740 src/main \uc544\ub798 java\uc640 webapp\uac00 \uc788\ub294\uac83 \uc774\ub2e4.",
                    "href": null
                }
            ],
            "color": "default"
        }
    },
    {
        "object": "block",
        "id": "1f422086-c5a0-80e1-b267-e52f12bd66c2",
        "parent": {
            "type": "page_id",
            "page_id": "1f422086-c5a0-807b-bd4d-ffe3502e74f8"
        },
        "created_time": "2025-05-15T16:11:00.000Z",
        "last_edited_time": "2025-05-15T16:15:00.000Z",
        "created_by": {
            "object": "user",
            "id": "66828f29-35c2-40b1-9346-8b0ef9c20741"
        },
        "last_edited_by": {
            "object": "user",
            "id": "66828f29-35c2-40b1-9346-8b0ef9c20741"
        },
        "has_children": false,
        "archived": false,
        "in_trash": false,
        "type": "paragraph",
        "paragraph": {
            "rich_text": [
                {
                    "type": "text",
                    "text": {
                        "content": "src/main/java : \ubc31\uc5d4\ub4dc \uc790\ubc14 \uc18c\uc2a4 \ucf54\ub4dc",
                        "link": null
                    },
                    "annotations": {
                        "bold": false,
                        "italic": false,
                        "strikethrough": false,
                        "underline": false,
                        "code": false,
                        "color": "default"
                    },
                    "plain_text": "src/main/java : \ubc31\uc5d4\ub4dc \uc790\ubc14 \uc18c\uc2a4 \ucf54\ub4dc",
                    "href": null
                }
            ],
            "color": "default"
        }
    },
    {
        "object": "block",
        "id": "1f422086-c5a0-801a-9ec9-e0d84da0bd00",
        "parent": {
            "type": "page_id",
            "page_id": "1f422086-c5a0-807b-bd4d-ffe3502e74f8"
        },
        "created_time": "2025-05-15T16:15:00.000Z",
        "last_edited_time": "2025-05-15T16:15:00.000Z",
        "created_by": {
            "object": "user",
            "id": "66828f29-35c2-40b1-9346-8b0ef9c20741"
        },
        "last_edited_by": {
            "object": "user",
            "id": "66828f29-35c2-40b1-9346-8b0ef9c20741"
        },
        "has_children": false,
        "archived": false,
        "in_trash": false,
        "type": "paragraph",
        "paragraph": {
            "rich_text": [
                {
                    "type": "text",
                    "text": {
                        "content": "src/main/webapp : \uc6f9 \ub9ac\uc18c\uc2a4 \ub8e8\ud2b8 \ub514\ub809\ud1a0\ub9ac",
                        "link": null
                    },
                    "annotations": {
                        "bold": false,
                        "italic": false,
                        "strikethrough": false,
                        "underline": false,
                        "code": false,
                        "color": "default"
                    },
                    "plain_text": "src/main/webapp : \uc6f9 \ub9ac\uc18c\uc2a4 \ub8e8\ud2b8 \ub514\ub809\ud1a0\ub9ac",
                    "href": null
                }
            ],
            "color": "default"
        }
    },
    {
        "object": "block",
        "id": "1f422086-c5a0-80da-b44a-e50ca722a0e6",
        "parent": {
            "type": "page_id",
            "page_id": "1f422086-c5a0-807b-bd4d-ffe3502e74f8"
        },
        "created_time": "2025-05-15T16:15:00.000Z",
        "last_edited_time": "2025-05-15T16:15:00.000Z",
        "created_by": {
            "object": "user",
            "id": "66828f29-35c2-40b1-9346-8b0ef9c20741"
        },
        "last_edited_by": {
            "object": "user",
            "id": "66828f29-35c2-40b1-9346-8b0ef9c20741"
        },
        "has_children": false,
        "archived": false,
        "in_trash": false,
        "type": "paragraph",
        "paragraph": {
            "rich_text": [
                {
                    "type": "text",
                    "text": {
                        "content": "src/main/resource : \ubc31\uc5d4\ub4dc \ub9ac\uc18c\uc2a4",
                        "link": null
                    },
                    "annotations": {
                        "bold": false,
                        "italic": false,
                        "strikethrough": false,
                        "underline": false,
                        "code": false,
                        "color": "default"
                    },
                    "plain_text": "src/main/resource : \ubc31\uc5d4\ub4dc \ub9ac\uc18c\uc2a4",
                    "href": null
                }
            ],
            "color": "default"
        }
    },
    {
        "object": "block",
        "id": "1f422086-c5a0-8055-8613-fb4f15723687",
        "parent": {
            "type": "page_id",
            "page_id": "1f422086-c5a0-807b-bd4d-ffe3502e74f8"
        },
        "created_time": "2025-05-15T16:16:00.000Z",
        "last_edited_time": "2025-05-15T16:16:00.000Z",
        "created_by": {
            "object": "user",
            "id": "66828f29-35c2-40b1-9346-8b0ef9c20741"
        },
        "last_edited_by": {
            "object": "user",
            "id": "66828f29-35c2-40b1-9346-8b0ef9c20741"
        },
        "has_children": false,
        "archived": false,
        "in_trash": false,
        "type": "paragraph",
        "paragraph": {
            "rich_text": [],
            "color": "default"
        }
    },
    {
        "object": "block",
        "id": "1f422086-c5a0-80de-880d-e2ccaf7b9536",
        "parent": {
            "type": "page_id",
            "page_id": "1f422086-c5a0-807b-bd4d-ffe3502e74f8"
        },
        "created_time": "2025-05-15T16:17:00.000Z",
        "last_edited_time": "2025-05-15T16:18:00.000Z",
        "created_by": {
            "object": "user",
            "id": "66828f29-35c2-40b1-9346-8b0ef9c20741"
        },
        "last_edited_by": {
            "object": "user",
            "id": "66828f29-35c2-40b1-9346-8b0ef9c20741"
        },
        "has_children": false,
        "archived": false,
        "in_trash": false,
        "type": "paragraph",
        "paragraph": {
            "rich_text": [
                {
                    "type": "text",
                    "text": {
                        "content": "\uadf8\ub7fc \uc65c \uc774\ud074\ub9bd\uc2a4\uc5d0\uc11c\ub294 src\uac00 \ub450\uac1c \uc778\uac83 \ucc98\ub7fc \ubcf4\uc5ec\uc904\uae4c?",
                        "link": null
                    },
                    "annotations": {
                        "bold": false,
                        "italic": false,
                        "strikethrough": false,
                        "underline": false,
                        "code": false,
                        "color": "default"
                    },
                    "plain_text": "\uadf8\ub7fc \uc65c \uc774\ud074\ub9bd\uc2a4\uc5d0\uc11c\ub294 src\uac00 \ub450\uac1c \uc778\uac83 \ucc98\ub7fc \ubcf4\uc5ec\uc904\uae4c?",
                    "href": null
                }
            ],
            "color": "default"
        }
    },
    {
        "object": "block",
        "id": "1f422086-c5a0-806e-861b-eeefadbd6d03",
        "parent": {
            "type": "page_id",
            "page_id": "1f422086-c5a0-807b-bd4d-ffe3502e74f8"
        },
        "created_time": "2025-05-15T16:16:00.000Z",
        "last_edited_time": "2025-05-15T16:19:00.000Z",
        "created_by": {
            "object": "user",
            "id": "66828f29-35c2-40b1-9346-8b0ef9c20741"
        },
        "last_edited_by": {
            "object": "user",
            "id": "66828f29-35c2-40b1-9346-8b0ef9c20741"
        },
        "has_children": false,
        "archived": false,
        "in_trash": false,
        "type": "paragraph",
        "paragraph": {
            "rich_text": [
                {
                    "type": "text",
                    "text": {
                        "content": "\ubcf4\uae30 \uc27d\uac8c \ub9cc\ub4e4\ub824\uace0",
                        "link": null
                    },
                    "annotations": {
                        "bold": false,
                        "italic": false,
                        "strikethrough": false,
                        "underline": false,
                        "code": false,
                        "color": "default"
                    },
                    "plain_text": "\ubcf4\uae30 \uc27d\uac8c \ub9cc\ub4e4\ub824\uace0",
                    "href": null
                }
            ],
            "color": "default"
        }
    },
    {
        "object": "block",
        "id": "1f422086-c5a0-803d-a928-e181d204b1d0",
        "parent": {
            "type": "page_id",
            "page_id": "1f422086-c5a0-807b-bd4d-ffe3502e74f8"
        },
        "created_time": "2025-05-15T16:19:00.000Z",
        "last_edited_time": "2025-05-15T16:19:00.000Z",
        "created_by": {
            "object": "user",
            "id": "66828f29-35c2-40b1-9346-8b0ef9c20741"
        },
        "last_edited_by": {
            "object": "user",
            "id": "66828f29-35c2-40b1-9346-8b0ef9c20741"
        },
        "has_children": false,
        "archived": false,
        "in_trash": false,
        "type": "paragraph",
        "paragraph": {
            "rich_text": [],
            "color": "default"
        }
    },
    {
        "object": "block",
        "id": "1f422086-c5a0-8013-9ec6-fe8cf661571c",
        "parent": {
            "type": "page_id",
            "page_id": "1f422086-c5a0-807b-bd4d-ffe3502e74f8"
        },
        "created_time": "2025-05-15T16:11:00.000Z",
        "last_edited_time": "2025-05-15T16:11:00.000Z",
        "created_by": {
            "object": "user",
            "id": "66828f29-35c2-40b1-9346-8b0ef9c20741"
        },
        "last_edited_by": {
            "object": "user",
            "id": "66828f29-35c2-40b1-9346-8b0ef9c20741"
        },
        "has_children": false,
        "archived": false,
        "in_trash": false,
        "type": "heading_1",
        "heading_1": {
            "rich_text": [
                {
                    "type": "text",
                    "text": {
                        "content": "Insight : ",
                        "link": null
                    },
                    "annotations": {
                        "bold": false,
                        "italic": false,
                        "strikethrough": false,
                        "underline": false,
                        "code": false,
                        "color": "default"
                    },
                    "plain_text": "Insight : ",
                    "href": null
                }
            ],
            "is_toggleable": false,
            "color": "default"
        }
    },
    {
        "object": "block",
        "id": "1f422086-c5a0-8050-b72d-f1dfd44da0ca",
        "parent": {
            "type": "page_id",
            "page_id": "1f422086-c5a0-807b-bd4d-ffe3502e74f8"
        },
        "created_time": "2025-05-15T16:11:00.000Z",
        "last_edited_time": "2025-05-15T16:11:00.000Z",
        "created_by": {
            "object": "user",
            "id": "66828f29-35c2-40b1-9346-8b0ef9c20741"
        },
        "last_edited_by": {
            "object": "user",
            "id": "66828f29-35c2-40b1-9346-8b0ef9c20741"
        },
        "has_children": false,
        "archived": false,
        "in_trash": false,
        "type": "paragraph",
        "paragraph": {
            "rich_text": [
                {
                    "type": "text",
                    "text": {
                        "content": "\ubb58 \ub290\uaf08\uc5b4?",
                        "link": null
                    },
                    "annotations": {
                        "bold": true,
                        "italic": false,
                        "strikethrough": false,
                        "underline": false,
                        "code": false,
                        "color": "gray"
                    },
                    "plain_text": "\ubb58 \ub290\uaf08\uc5b4?",
                    "href": null
                }
            ],
            "color": "default"
        }
    },
    {
        "object": "block",
        "id": "1f422086-c5a0-801a-ab42-c12e68b289c5",
        "parent": {
            "type": "page_id",
            "page_id": "1f422086-c5a0-807b-bd4d-ffe3502e74f8"
        },
        "created_time": "2025-05-15T16:11:00.000Z",
        "last_edited_time": "2025-05-15T16:11:00.000Z",
        "created_by": {
            "object": "user",
            "id": "66828f29-35c2-40b1-9346-8b0ef9c20741"
        },
        "last_edited_by": {
            "object": "user",
            "id": "66828f29-35c2-40b1-9346-8b0ef9c20741"
        },
        "has_children": false,
        "archived": false,
        "in_trash": false,
        "type": "heading_2",
        "heading_2": {
            "rich_text": [
                {
                    "type": "text",
                    "text": {
                        "content": "\uc798\ud55c\uc810",
                        "link": null
                    },
                    "annotations": {
                        "bold": false,
                        "italic": false,
                        "strikethrough": false,
                        "underline": false,
                        "code": false,
                        "color": "default"
                    },
                    "plain_text": "\uc798\ud55c\uc810",
                    "href": null
                }
            ],
            "is_toggleable": false,
            "color": "default"
        }
    },
    {
        "object": "block",
        "id": "1f422086-c5a0-802d-9a5e-c6645d511f5c",
        "parent": {
            "type": "page_id",
            "page_id": "1f422086-c5a0-807b-bd4d-ffe3502e74f8"
        },
        "created_time": "2025-05-15T16:11:00.000Z",
        "last_edited_time": "2025-05-15T16:11:00.000Z",
        "created_by": {
            "object": "user",
            "id": "66828f29-35c2-40b1-9346-8b0ef9c20741"
        },
        "last_edited_by": {
            "object": "user",
            "id": "66828f29-35c2-40b1-9346-8b0ef9c20741"
        },
        "has_children": false,
        "archived": false,
        "in_trash": false,
        "type": "heading_2",
        "heading_2": {
            "rich_text": [
                {
                    "type": "text",
                    "text": {
                        "content": "\uac1c\uc120\uc810",
                        "link": null
                    },
                    "annotations": {
                        "bold": false,
                        "italic": false,
                        "strikethrough": false,
                        "underline": false,
                        "code": false,
                        "color": "default"
                    },
                    "plain_text": "\uac1c\uc120\uc810",
                    "href": null
                }
            ],
            "is_toggleable": false,
            "color": "default"
        }
    },
    {
        "object": "block",
        "id": "1f422086-c5a0-80e7-bc6d-f2948cb75943",
        "parent": {
            "type": "page_id",
            "page_id": "1f422086-c5a0-807b-bd4d-ffe3502e74f8"
        },
        "created_time": "2025-05-15T16:11:00.000Z",
        "last_edited_time": "2025-05-15T16:11:00.000Z",
        "created_by": {
            "object": "user",
            "id": "66828f29-35c2-40b1-9346-8b0ef9c20741"
        },
        "last_edited_by": {
            "object": "user",
            "id": "66828f29-35c2-40b1-9346-8b0ef9c20741"
        },
        "has_children": false,
        "archived": false,
        "in_trash": false,
        "type": "heading_2",
        "heading_2": {
            "rich_text": [
                {
                    "type": "text",
                    "text": {
                        "content": "\ubc30\uc6b8\uc810",
                        "link": null
                    },
                    "annotations": {
                        "bold": false,
                        "italic": false,
                        "strikethrough": false,
                        "underline": false,
                        "code": false,
                        "color": "default"
                    },
                    "plain_text": "\ubc30\uc6b8\uc810",
                    "href": null
                }
            ],
            "is_toggleable": false,
            "color": "default"
        }
    }
]